boadata/__init__.py
boadata/cli/__init__.py
boadata/commands/__init__.py
boadata/commands/boacat.py
boadata/commands/boaconvert.py
boadata/commands/boadescribe.py
boadata/commands/boatable.py
boadata/commands/boatree.py
boadata/core/__init__.py
boadata/core/data_conversion.py
boadata/core/data_node.py
boadata/core/data_object.py
boadata/core/data_properties.py
boadata/core/data_tree.py
boadata/data/__init__.py
boadata/data/avro_types.py
boadata/data/csv_types.py
boadata/data/dw_types.py
boadata/data/excel_types.py
boadata/data/feather_types.py
boadata/data/field_types.py
boadata/data/geant4_types.py
boadata/data/hdf5_types.py
boadata/data/json_types.py
boadata/data/matlab_types.py
boadata/data/mixins.py
boadata/data/narwhals_types.py
boadata/data/numpy_types.py
boadata/data/pandas_types.py
boadata/data/parquet_types.py
boadata/data/plotting_types.py
boadata/data/polars_types.py
boadata/data/pydataset_types.py
boadata/data/sql_types.py
boadata/data/text_types.py
boadata/data/xarray_types.py
boadata/trees/__init__.py
boadata/trees/dw.py
boadata/trees/excel.py
boadata/trees/file.py
boadata/trees/generic.py
boadata/trees/google_storage.py
boadata/trees/hdf5.py
boadata/trees/matlab.py
boadata/trees/pydaset.py
boadata/trees/sql.py
boadata-0.4.2.dist-info/entry_points.txt
boadata-0.4.2.dist-info/licenses/LICENSE
boadata-0.4.2.dist-info/WHEEL
boadata-0.4.2.dist-info/METADATA
boadata-0.4.2.dist-info/RECORD
