Metadata-Version: 2.4
Name: boadata
Version: 0.4.2
Summary: (B)rother (O)f (A)rbitrary Data - Python CLI tools for data.
Author-email: Jan Pipek <jan.pipek@gmail.com>
Requires-Python: >=3.11,<3.15
License-Expression: MIT
Classifier: Programming Language :: Python :: 3.11
Classifier: Programming Language :: Python :: 3.12
Classifier: Programming Language :: Python :: 3.13
Classifier: Development Status :: 3 - Alpha
Classifier: Operating System :: OS Independent
Classifier: Intended Audience :: Developers
Classifier: Intended Audience :: Information Technology
Classifier: Intended Audience :: Science/Research
Classifier: Topic :: Scientific/Engineering
Classifier: Topic :: Software Development :: Libraries :: Python Modules
License-File: LICENSE
Requires-Dist: numpy>1.21
Requires-Dist: pandas>2.0
Requires-Dist: scipy>=1.14.1
Requires-Dist: blinker
Requires-Dist: sqlalchemy
Requires-Dist: numexpr
Requires-Dist: click
Requires-Dist: xarray
Requires-Dist: scipy
Requires-Dist: matplotlib
Requires-Dist: seaborn
Requires-Dist: tabulate
Requires-Dist: physt
Requires-Dist: typer
Requires-Dist: textual
Requires-Dist: clevercsv>=0.8.2
Requires-Dist: textual-fastdatatable>=0.10.0
Requires-Dist: polars>=1.33.1
Requires-Dist: narwhals>=2.5.0
Requires-Dist: fastavro ; extra == "avro"
Requires-Dist: openpyxl ; extra == "excel"
Requires-Dist: xlrd ; extra == "excel"
Requires-Dist: google-cloud-storage ; extra == "google-cloud"
Requires-Dist: h5py ; extra == "h5py"
Requires-Dist: pydons ; extra == "matlab"
Requires-Dist: pydataset ; extra == "pydataset"
Provides-Extra: avro
Provides-Extra: excel
Provides-Extra: google-cloud
Provides-Extra: h5py
Provides-Extra: matlab
Provides-Extra: pydataset
